libtcodpy.py
tcod-19.6.1.dist-info/RECORD
tcod-19.6.1.dist-info/WHEEL
tcod-19.6.1.dist-info/entry_points.txt
tcod-19.6.1.dist-info/top_level.txt
tcod-19.6.1.dist-info/METADATA
tcod-19.6.1.dist-info/licenses/LICENSE.txt
tcod-19.6.1.dist-info/licenses/libtcod/LIBTCOD-CREDITS.txt
tcod-19.6.1.dist-info/licenses/libtcod/LICENSE.txt
tcod/event_constants.py
tcod/console.py
tcod/noise.h
tcod/event.py
tcod/color.py
tcod/version.py
tcod/_internal.py
tcod/path.h
tcod/render.py
tcod/cffi.py
tcod/bsp.py
tcod/constants.py
tcod/tcod.c
tcod/tcod.py
tcod/__init__.py
tcod/tileset.py
tcod/random.py
tcod/map.py
tcod/noise.c
tcod/context.py
tcod/path.c
tcod/noise.py
tcod/los.py
tcod/py.typed
tcod/libtcodpy.py
tcod/cffi.h
tcod/tcod.h
tcod/_libtcod.pyi
tcod/cdef.h
tcod/path.py
tcod/image.py
tcod/_libtcod.pypy310-pp73-darwin.so
tcod/random.h
tcod/__pyinstaller/__init__.py
tcod/__pyinstaller/hook-tcod.py
tcod/.dylibs/SDL3
tcod/sdl/_internal.py
tcod/sdl/render.py
tcod/sdl/constants.py
tcod/sdl/__init__.py
tcod/sdl/joystick.py
tcod/sdl/mouse.py
tcod/sdl/audio.py
tcod/sdl/video.py
tcod/sdl/sys.py
