Metadata-Version: 2.4
Name: tcod
Version: 19.6.1
Summary: The official Python port of libtcod.
Author-email: Kyle Benesch <4b796c65+tcod@gmail.com>
License-Expression: BSD-2-Clause
Project-URL: Homepage, https://github.com/libtcod/python-tcod
Project-URL: Documentation, https://python-tcod.readthedocs.io
Project-URL: Changelog, https://github.com/libtcod/python-tcod/blob/main/CHANGELOG.md
Project-URL: Source, https://github.com/libtcod/python-tcod
Project-URL: Tracker, https://github.com/libtcod/python-tcod/issues
Project-URL: Forum, https://github.com/libtcod/python-tcod/discussions
Keywords: roguelike,cffi,Unicode,libtcod,field-of-view,pathfinding
Platform: Windows
Platform: MacOS
Platform: Linux
Classifier: Development Status :: 5 - Production/Stable
Classifier: Environment :: Win32 (MS Windows)
Classifier: Environment :: MacOS X
Classifier: Environment :: X11 Applications
Classifier: Intended Audience :: Developers
Classifier: Natural Language :: English
Classifier: Operating System :: POSIX
Classifier: Operating System :: MacOS :: MacOS X
Classifier: Operating System :: Microsoft :: Windows
Classifier: Programming Language :: Python :: 3
Classifier: Programming Language :: Python :: 3.10
Classifier: Programming Language :: Python :: 3.11
Classifier: Programming Language :: Python :: 3.12
Classifier: Programming Language :: Python :: 3.13
Classifier: Programming Language :: Python :: Implementation :: CPython
Classifier: Programming Language :: Python :: Implementation :: PyPy
Classifier: Topic :: Games/Entertainment
Classifier: Topic :: Multimedia :: Graphics
Classifier: Topic :: Software Development :: Libraries :: Python Modules
Classifier: Typing :: Typed
Requires-Python: >=3.10
License-File: LICENSE.txt
License-File: libtcod/LICENSE.txt
License-File: libtcod/LIBTCOD-CREDITS.txt
Requires-Dist: cffi>=1.15
Requires-Dist: numpy>=1.21.4; implementation_name != "pypy"
Requires-Dist: typing_extensions>=4.12.2
Dynamic: license-file
Dynamic: platform
